gradientcolors/__init__.py
gradientcolors/gradientcolors_file.py
gradientcolors-5.dist-info/METADATA
gradientcolors-5.dist-info/WHEEL
gradientcolors-5.dist-info/top_level.txt
gradientcolors-5.dist-info/RECORD
