Metadata-Version: 2.1
Name: gradientcolors
Version: 5
Summary: Pure-python Colors implementation
Home-page: https://github.com/pwaller/pyfiglet
Author: Peter Waller (Thanks to Christopher Jones and Stefano Rivera)
Author-email: p@pwaller.net
Classifier: Development Status :: 3 - Alpha
Classifier: Intended Audience :: Developers
Classifier: License :: OSI Approved :: MIT License
Classifier: Programming Language :: Python :: 3
Classifier: Programming Language :: Python :: 3.6
Classifier: Programming Language :: Python :: 3.7
Classifier: Programming Language :: Python :: 3.8
Classifier: Programming Language :: Python :: 3.9
Classifier: Programming Language :: Python :: 3.10
Classifier: Programming Language :: Python :: 3
Classifier: Operating System :: Microsoft :: Windows
Requires-Dist: requests
Requires-Dist: colorama
